whois_mcp/__init__.py
whois_mcp/__main__.py
whois_mcp/cli.py
whois_mcp/test_query.py
whois_mcp/whois_api.py
whois_mcp_server-0.1.5.dist-info/METADATA
whois_mcp_server-0.1.5.dist-info/WHEEL
whois_mcp_server-0.1.5.dist-info/entry_points.txt
whois_mcp_server-0.1.5.dist-info/top_level.txt
whois_mcp_server-0.1.5.dist-info/RECORD
